pymilvus/__init__.py
pymilvus/decorators.py
pymilvus/exceptions.py
pymilvus/settings.py
pymilvus/bulk_writer/__init__.py
pymilvus/bulk_writer/buffer.py
pymilvus/bulk_writer/bulk_import.py
pymilvus/bulk_writer/bulk_writer.py
pymilvus/bulk_writer/constants.py
pymilvus/bulk_writer/endpoint_resolver.py
pymilvus/bulk_writer/file_utils.py
pymilvus/bulk_writer/local_bulk_writer.py
pymilvus/bulk_writer/remote_bulk_writer.py
pymilvus/bulk_writer/stage_bulk_writer.py
pymilvus/bulk_writer/stage_file_manager.py
pymilvus/bulk_writer/stage_manager.py
pymilvus/bulk_writer/stage_restful.py
pymilvus/bulk_writer/validators.py
pymilvus/client/__init__.py
pymilvus/client/abstract.py
pymilvus/client/async_grpc_handler.py
pymilvus/client/async_interceptor.py
pymilvus/client/asynch.py
pymilvus/client/blob.py
pymilvus/client/check.py
pymilvus/client/constants.py
pymilvus/client/entity_helper.py
pymilvus/client/grpc_handler.py
pymilvus/client/interceptor.py
pymilvus/client/prepare.py
pymilvus/client/search_iterator.py
pymilvus/client/search_result.py
pymilvus/client/singleton_utils.py
pymilvus/client/ts_utils.py
pymilvus/client/types.py
pymilvus/client/utils.py
pymilvus/grpc_gen/__init__.py
pymilvus/grpc_gen/common_pb2.py
pymilvus/grpc_gen/common_pb2.pyi
pymilvus/grpc_gen/feder_pb2.py
pymilvus/grpc_gen/feder_pb2.pyi
pymilvus/grpc_gen/milvus_pb2.py
pymilvus/grpc_gen/milvus_pb2.pyi
pymilvus/grpc_gen/milvus_pb2_grpc.py
pymilvus/grpc_gen/msg_pb2.py
pymilvus/grpc_gen/msg_pb2.pyi
pymilvus/grpc_gen/python_gen.sh
pymilvus/grpc_gen/rg_pb2.py
pymilvus/grpc_gen/rg_pb2.pyi
pymilvus/grpc_gen/schema_pb2.py
pymilvus/grpc_gen/schema_pb2.pyi
pymilvus/milvus_client/__init__.py
pymilvus/milvus_client/_utils.py
pymilvus/milvus_client/async_milvus_client.py
pymilvus/milvus_client/check.py
pymilvus/milvus_client/index.py
pymilvus/milvus_client/milvus_client.py
pymilvus/orm/__init__.py
pymilvus/orm/collection.py
pymilvus/orm/connections.py
pymilvus/orm/constants.py
pymilvus/orm/db.py
pymilvus/orm/future.py
pymilvus-2.5.17.dist-info/licenses/LICENSE
pymilvus-2.5.17.dist-info/METADATA
pymilvus-2.5.17.dist-info/WHEEL
pymilvus-2.5.17.dist-info/top_level.txt
pymilvus-2.5.17.dist-info/RECORD
