Metadata-Version: 2.4
Name: pymilvus
Version: 2.5.17
Summary: Python Sdk for Milvus
Author-email: Milvus Team <milvus-team@zilliz.com>
Project-URL: repository, https://github.com/milvus-io/pymilvus
Classifier: Programming Language :: Python :: 3
Classifier: Programming Language :: Python :: 3.8
Classifier: Programming Language :: Python :: 3.9
Classifier: Programming Language :: Python :: 3.10
Classifier: Programming Language :: Python :: 3.11
Classifier: Programming Language :: Python :: 3.12
Classifier: Programming Language :: Python :: 3.13
Classifier: License :: OSI Approved :: Apache Software License
Requires-Python: >=3.8
License-File: LICENSE
Requires-Dist: setuptools>69
Requires-Dist: setuptools<70.1; python_version <= "3.8"
Requires-Dist: protobuf>=3.20.0
Requires-Dist: grpcio!=1.68.0,!=1.68.1,!=1.69.0,!=1.70.0,!=1.70.1,!=1.71.0,!=1.72.1,!=1.73.0,>=1.49.1
Requires-Dist: python-dotenv<2.0.0,>=1.0.1
Requires-Dist: ujson>=2.0.0
Requires-Dist: pandas>=1.2.4
Requires-Dist: numpy<1.25.0; python_version <= "3.8"
Requires-Dist: milvus-lite>=2.4.0; sys_platform != "win32"
Provides-Extra: bulk-writer
Requires-Dist: requests; extra == "bulk-writer"
Requires-Dist: minio>=7.0.0; extra == "bulk-writer"
Requires-Dist: pyarrow>=12.0.0; extra == "bulk-writer"
Requires-Dist: azure-storage-blob; extra == "bulk-writer"
Requires-Dist: urllib3; extra == "bulk-writer"
Provides-Extra: model
Requires-Dist: pymilvus.model>=0.3.0; extra == "model"
Provides-Extra: dev
Requires-Dist: grpcio==1.62.2; extra == "dev"
Requires-Dist: grpcio-tools==1.62.2; extra == "dev"
Requires-Dist: grpcio-testing==1.62.2; extra == "dev"
Requires-Dist: pytest>=5.3.4; extra == "dev"
Requires-Dist: pytest-cov>=2.8.1; extra == "dev"
Requires-Dist: pytest-timeout>=1.3.4; extra == "dev"
Requires-Dist: pytest-asyncio; extra == "dev"
Requires-Dist: ruff<1,>=0.12.9; extra == "dev"
Requires-Dist: black; extra == "dev"
Dynamic: license-file
